excel_97/__init__.py
excel_97/excel97.py
excel97_py-0.1.2.dist-info/LICENSE
excel97_py-0.1.2.dist-info/METADATA
excel97_py-0.1.2.dist-info/WHEEL
excel97_py-0.1.2.dist-info/top_level.txt
excel97_py-0.1.2.dist-info/RECORD
