Metadata-Version: 2.1
Name: excel97_py
Version: 0.1.2
Summary: A Python library to manipulate Excel 97/2003 spreadsheet files
Home-page: https://github.com/sandy98/dbase3-py
Author: Domingo E. Savoretti
Author-email: esavoretti@gmail.com
License: UNKNOWN
Platform: UNKNOWN
Classifier: Programming Language :: Python :: 3
Classifier: License :: OSI Approved :: MIT License
Classifier: Operating System :: OS Independent
Requires-Python: >=3.6
License-File: LICENSE
